drake.cpython-313-x86_64-linux-gnu.so
drake/__init__.py
drake/lcmt_acrobot_u.py
drake/lcmt_acrobot_x.py
drake/lcmt_acrobot_y.py
drake/lcmt_allegro_command.py
drake/lcmt_allegro_status.py
drake/lcmt_call_python.py
drake/lcmt_call_python_data.py
drake/lcmt_contact_results_for_viz.py
drake/lcmt_drake_signal.py
drake/lcmt_force_torque.py
drake/lcmt_header.py
drake/lcmt_hydroelastic_contact_surface_for_viz.py
drake/lcmt_hydroelastic_quadrature_per_point_data_for_viz.py
drake/lcmt_iiwa_command.py
drake/lcmt_iiwa_status.py
drake/lcmt_iiwa_status_telemetry.py
drake/lcmt_image.py
drake/lcmt_image_array.py
drake/lcmt_jaco_command.py
drake/lcmt_jaco_status.py
drake/lcmt_panda_command.py
drake/lcmt_panda_status.py
drake/lcmt_planar_gripper_command.py
drake/lcmt_planar_gripper_finger_command.py
drake/lcmt_planar_gripper_finger_face_assignment.py
drake/lcmt_planar_gripper_finger_face_assignments.py
drake/lcmt_planar_gripper_finger_status.py
drake/lcmt_planar_gripper_status.py
drake/lcmt_planar_manipuland_status.py
drake/lcmt_planar_plant_state.py
drake/lcmt_point.py
drake/lcmt_point_cloud.py
drake/lcmt_point_cloud_field.py
drake/lcmt_point_pair_contact_info_for_viz.py
drake/lcmt_quaternion.py
drake/lcmt_robot_plan.py
drake/lcmt_robot_state.py
drake/lcmt_schunk_wsg_command.py
drake/lcmt_schunk_wsg_status.py
drake/lcmt_scope.py
drake/lcmt_viewer_command.py
drake/lcmt_viewer_draw.py
drake/lcmt_viewer_geometry_data.py
drake/lcmt_viewer_link_data.py
drake/lcmt_viewer_load_robot.py
drake.libs/libgfortran-2a0033af.so.5.0.0
drake.libs/libgomp-273d0f96.so.1.0.0
drake.libs/libquadmath-35e40273.so.0.0.0
pydrake/INSTALLATION
pydrake/__init__.py
pydrake/_all_everything.py
pydrake/_lcm_extra.py
pydrake/_trajectories_extra.py
pydrake/all.py
pydrake/autodiffutils.pyi
pydrake/examples.pyi
pydrake/forwarddiff.py
pydrake/lcm.pyi
pydrake/lcm.so
pydrake/manipulation.pyi
pydrake/math.pyi
pydrake/perception.pyi
pydrake/perception.so
drake-1.49.0.dist-info/METADATA
drake-1.49.0.dist-info/WHEEL
drake-1.49.0.dist-info/top_level.txt
drake-1.49.0.dist-info/RECORD
drake-1.49.0.dist-info/sboms/auditwheel.cdx.json
